Laboratorio_09/Ejercicio 2/Ejercicio2.v
//Ejercicio 2: Flip Flop Tipo T
//Daniel Mundo 19508
module FlipFlopT(input eneable, reset, clk, output wire Q);
  FlipFlopD f1(eneable, reset, clk, ~Q, Q);
endmodule //Este modulo describe que durante cada flanco de reloj la entrada "D"
          //del FlipFlop tipo D es el valor inverso de la salida actual "Q".
module FlipFlopD(input eneable1, reset1, clk1, input D, output reg Q1);
  always @ (posedge clk1, posedge reset1)
  begin
    if (reset1) Q1 <= 1'b0;
    else if (eneable1) Q1 <= D;
    end
endmodule //Del ejercicio 1, el funcionamiento se explica en el archivo:
        // "Ejercicio1.v", carpeta Ejercicio 1.

Laboratorio_09/Ejercicio 2/Ejercicio2_tb.v
//Test Bench: Ejercicio 2
module testbench();
reg clk;
reg reset;
reg eneable;
wire Q; //Se define el tipo de "variable" con las cuales va a trabajar
      //el modulo.
FlipFlopD f3(eneable, reset, clk, ~Q, Q); //Se llama al modulo.
initial begin
clk = 0; reset = 1; eneable = 1;
#1 reset = 0;
#10 eneable = 0; reset = 1;
#3 eneable = 1; reset = 0;
#10 $finish;
end //Es el apartado de las pruebas asignadoles valores a las entradas.
always
#1 clk = !clk; //Se invierte el valor de clk, para simular una verdadera
              //señal de reloj.
initial begin
  $dumpfile("Ejercicio2_tb.vcd");
  $dumpvars(0, testbench);
end  //Se crea el archivo para mostrar las pruebas.
endmodule

Laboratorio_09/Ejercicio 2/Ejercicio2_tb.vcd
$date
	Sat Oct 31 02:14:36 2020
$end
$version
	Icarus Verilog
$end
$timescale
	1ps
$end
$scope module testbench $end
$var wire 1 ! Q $end
$var reg 1 " clk $end
$var reg 1 # eneable $end
$var reg 1 $ reset $end
$scope module f3 $end
$var wire 1 % D $end
$var wire 1 " clk1 $end
$var wire 1 # eneable1 $end
$var wire 1 $ reset1 $end
$var reg 1 ! Q1 $end
$upscope $end
$upscope $end
$enddefinitions $end
#0
$dumpvars
1%
1$
1#
0"
0!
$end
#1
0%
1!
1"
0$
#2
0"
#3
1%
0!
1"
#4
0"
#5
0%
1!
1"
#6
0"
#7
1%
0!
1"
#8
0"
#9
0%
1!
1"
#10
0"
#11
1%
0!
1"
1$
0#
#12
0"
#13
1"
#14
0"
0$
1#
#15
0%
1!
1"
#16
0"
#17
1%
0!
1"
#18
0"
#19
0%
1!
1"
#20
0"
#21
1%
0!
1"
#22
0"
#23
0%
1!
1"
