Laboratorio_10/Ejercicio_1/Memoria.v
//Ejercicio 2: Memoria ROM
//Daniel Mundo 19508
module ROM(input wire [11:0]direccion,
            output wire [7:0]dato);
  reg [7:0] Memoria [0:4095];
  initial begin
    $readmemh("Archivo_Hex.txt", Memoria);
  end
  assign dato = Memoria[direccion];

endmodule

Laboratorio_08/Ejercicio_2/Ejercicio2_tb.v
//Ejercicio 2
module testbench();

reg [11:0] P;
wire [7:0] D;

ROM mem(P,D);

initial
begin
#1
  $display("--------------ROM-------------");
  $display("|    Localidad  |     Dato   |");
  $monitor("| %b  |  %b  |", P, D);
     P = 12'h000;
  #5 P = 12'h001;
  #5 P = 12'h002;
  #5 P = 12'h003;
  #5 P = 12'h004;
  #5 P = 12'h005;
  #5 P = 12'h006;
  #5 P = 12'h007;
  #5 P = 12'h008;
  #5 P = 12'h009;
  #5 P = 12'h00A;
  #500 $finish;
end

initial begin
       $dumpfile("Ejercicio2_tb.vcd");
       $dumpvars(0,testbench);
   end

endmodule

Laboratorio_08/Ejercicio_2/Ejercicio2_tb.vcd
$date
	Sat Oct 24 20:47:31 2020
$end
$version
	Icarus Verilog
$end
$timescale
	1ps
$end
$scope module testbench $end
$var wire 8 ! D [7:0] $end
$var reg 12 " P [11:0] $end
$scope module mem $end
$var wire 8 # dato [7:0] $end
$var wire 12 $ direccion [11:0] $end
$upscope $end
$upscope $end
$enddefinitions $end
#0
$dumpvars
bx $
bx #
bx "
bx !
$end
#1
b1111 !
b1111 #
b0 "
b0 $
#6
b11110000 !
b11110000 #
b1 "
b1 $
#11
b10100001 !
b10100001 #
b10 "
b10 $
#16
b10101110 !
b10101110 #
b11 "
b11 $
#21
b1101011 !
b1101011 #
b100 "
b100 $
#26
b10001100 !
b10001100 #
b101 "
b101 $
#31
b10011111 !
b10011111 #
b110 "
b110 $
#36
b11110111 !
b11110111 #
b111 "
b111 $
#41
b11101110 !
b11101110 #
b1000 "
b1000 $
#46
b11111111 !
b11111111 #
b1001 "
b1001 $
#51
b0 !
b0 #
b1010 "
b1010 $
