Laboratorio_03/T2_SOP/T2SOP.v
//Nombre del modulo
module T2SOP();

// Entradas
reg a, b, c;
// Salidas
wire M1, M2, M3;
wire notA, notB, notC;
wire Y;

// Negacion de entradas
not N1(notA, a);
not N2(notB, b);
not N3(notC, c);

// Minterminos
and A1(M1, notA, notB, c);
and A2(M2, a, b, notC);
and A3(M3, a, b, c);
or O4(Y, M1, M2, M3);
//Condiciones
initial begin
  $monitor ("a=%b, b=%b, c=%b, Y=%b", a, b, c, Y);
  a =0; b =0; c =0;
  #1 a =1;
  #1 b =1;
  #1 b =0; c =1;
  #1 a =0; b =1; c =0;
  #1 c =1;
  #1 b =0;
  #1 a =1; b =1; $finish;
end

initial
  begin
    $dumpfile("T2SOP_tb.vcd");
    $dumpvars(0, T2SOP);
  end
endmodule

Laboratorio_03/T2_SOP/T2SOP_tb.vcd
$date
	Sun Aug 02 17:06:22 2020
$end
$version
	Icarus Verilog
$end
$timescale
	1ps
$end
$scope module T2SOP $end
$var wire 1 ! M1 $end
$var wire 1 " M2 $end
$var wire 1 # M3 $end
$var wire 1 $ Y $end
$var wire 1 % notA $end
$var wire 1 & notB $end
$var wire 1 ' notC $end
$var reg 1 ( a $end
$var reg 1 ) b $end
$var reg 1 * c $end
$upscope $end
$enddefinitions $end
#0
$dumpvars
0*
0)
0(
1'
1&
1%
0$
0#
0"
0!
$end
#1
0%
1(
#2
1$
1"
0&
1)
#3
0$
0'
0"
1&
1*
0)
#4
1'
0&
1%
0*
1)
0(
#5
0'
1*
#6
1$
1!
1&
0)
#7
0!
0&
1#
0%
1)
1(
