Laboratorio_03/T3_SOP/T3SOP.v
//Nombre del modulo
module T3SOP();

// Entradas
reg a, b, c, d;
// Salidas
wire M1, M2, M3, M4, M5, M6, M7;
wire notA, notB, notC, notD;
wire Y;

// Negacion de entradas
not N1(notA, a);
not N2(notB, b);
not N3(notC, c);
not N4(notD, d);

// Minterminos
and A1(M1, notA, notB, notC, notD);
and A2(M2, notA, notB, notC, d);
and A3(M3, notA, notB, c, notD);
and A4(M4, notA, notB, c, d);
and A5(M5, a, notB, notC, notD);
and A6(M6, a, notB, c, notD);
and A7(M7, a, b, c, notD);
or O10(Y, M1, M2, M3, M4, M5, M6, M7);

//Condiciones
initial begin
  $monitor ("a=%b, b=%b, c=%b, d=%b, Y=%b", a, b, c, d, Y);
  a =0; b =0; c =0; d=0;
  #1 a =1;                             //1000
  #1 a =0; b =1;                       //0100
  #1 b =0; c =1;                       //0010
  #1 c =0; d =1;                       //0001
  #1 c =1;                             //0011
  #1 a =1; c =0;                       //1001
  #1 a =0; b =1;                       //0101
  #1 a =1; d =0;                       //1100
  #1 a =0; c =1;                       //0110
  #1 a =1; b =0;                       //1010
  #1 a =0; b =1; d =1;                 //0111
  #1 a =1; b =0;                       //1011
  #1 b =1; c =0;                       //1101
  #1 c =1; d =0;                       //1110
  #1 d =1; $finish;                    //1111
end

initial
  begin
    $dumpfile("T3SOP_tb.vcd");
    $dumpvars(0, T3SOP);
  end
endmodule

Laboratorio_03/T3_SOP/T3SOP_tb.vcd
$date
	Sun Aug 02 17:05:09 2020
$end
$version
	Icarus Verilog
$end
$timescale
	1ps
$end
$scope module T3SOP $end
$var wire 1 ! M1 $end
$var wire 1 " M2 $end
$var wire 1 # M3 $end
$var wire 1 $ M4 $end
$var wire 1 % M5 $end
$var wire 1 & M6 $end
$var wire 1 ' M7 $end
$var wire 1 ( Y $end
$var wire 1 ) notA $end
$var wire 1 * notB $end
$var wire 1 + notC $end
$var wire 1 , notD $end
$var reg 1 - a $end
$var reg 1 . b $end
$var reg 1 / c $end
$var reg 1 0 d $end
$upscope $end
$enddefinitions $end
#0
$dumpvars
00
0/
0.
0-
1,
1+
1*
1)
1(
0'
0&
0%
0$
0#
0"
1!
$end
#1
0!
1%
0)
1-
#2
0(
0*
0%
1)
1.
0-
#3
1(
1#
0+
1*
1/
0.
#4
1"
0,
0#
1+
10
0/
#5
0"
1$
0+
1/
#6
0(
0$
1+
0)
0/
1-
#7
0*
1)
1.
0-
#8
1,
0)
00
1-
#9
0+
1)
1/
0-
#10
1(
1&
1*
0)
0.
1-
#11
0(
0,
0*
0&
1)
10
1.
0-
#12
1*
0)
0.
1-
#13
1+
0*
0/
1.
#14
1(
1'
1,
0+
00
1/
#15
0(
0'
0,
10
