Laboratorio_10/Ejercicio_1/Circuito1.v
//Ejercicio 1: Ciurcuito 1
//Daniel Mundo 19508
module FlipFlopD(input wire eneable2, reset2, clk2, input wire [7:0]D,
                  output reg [3:0] Q0, Q1);
  always @ (posedge clk2, posedge reset2) begin
    if (reset2) begin
        Q0 <= 0;
        Q1 <= 0;
    end
    else if (eneable2) begin
        Q1 <= D[3:0];
        Q0 <= D[7:4];
    end
  end
endmodule //El modulo describe que durante el flanco positivo de "clk" va reali-
        //zar la operacion de comprobar si "reset" esta encendido o no, en caso
        //afirmativo la salida "Q" es igual a 0 sino es igual al valor en ese
        //instante de la entrada "D".
//------------------------------------------------------------------------------
module circuito(input wire [11:0] valor,
                input wire eneable_fetch, eneable_counter, reset, clk, load,
                output wire [3:0] instr, oprnd, output wire [7:0] prog_b);
    wire [11:0] count_w;
    //wire [7:0] prog_b;
    counter_12b c0(eneable_counter, reset, clk, load, valor, count_w);
    ROM r0(count_w, prog_b);
    FlipFlopD f0(eneable_fetch, reset, clk, prog_b, instr, oprnd);
endmodule

Laboratorio_10/Ejercicio_1/Memoria.v
//Ejercicio 2: Memoria ROM
//Daniel Mundo 19508
module ROM(input wire [11:0]direccion,
            output wire [7:0]dato);
  reg [7:0] Memoria [0:4095];
  initial begin
    $readmemh("Archivo_Hex.txt", Memoria);
  end
  assign dato = Memoria[direccion];

endmodule

Laboratorio_08/Ejercicio_1/Ejercicio1.v
//Ejercicio 1: Contador con load
//Daniel Mundo 19508
module counter_12b(input clk, reset, load, eneable,
                  input [11:0] b,
                  output reg [11:0] c);
always @ (posedge clk)
begin
    if (reset)
      c <= 12'b0;
    else if (load)
      c <= b;
    if (eneable)
    begin
      if (c == 12'b111111111111)
      c <= 12'b0;
    else
      c <= c + 12'b000000000001;
      end
end
endmodule //counter

Laboratorio_10/Ejercicio_1/Circuito1_tb.v
//Ejercicio 1
module testbench();
reg [11:0] count;
reg load;
reg clk;
reg reset;
reg  eneable_counter, eneable_fetch;
wire [3:0] Intrucciones, Operand;
wire [7:0] program_byte; //Se define el tipo de "variable" con las cuales va a
            //trabajar el modulo.
circuito c1(count[11:0], eneable_fetch, eneable_counter,  reset, clk, load,
            Intrucciones[3:0], Operand[3:0], program_byte[7:0]); //Se llaman a los modulos.
initial begin
clk = 0; reset = 1; eneable_fetch = 0; eneable_counter = 0; count = 12'h000; load = 1;
#1 reset = 0;
#1 load = 0;
#1 eneable_counter = 1;
#1 count =12'h001;
#1 eneable_fetch = 1;
#10 eneable_counter = 0;
#6 reset = 1;
#1 load = 1;
#1 load = 0;
#1 reset = 0;
#3 eneable_counter = 1;
#50 $finish;
end //Es el apartado de las pruebas asignadoles valores a las entradas.
always
#1 clk = !clk;//Se invierte el valor de clk, para simular una verdadera
              //señal de reloj.
initial begin
  $dumpfile("Circuito1_tb.vcd");
  $dumpvars(0, testbench);
end //Se crea el archivo para mostrar las pruebas.
endmodule

Laboratorio_10/Ejercicio_1/Circuito1_tb.vcd
$date
	Sun Nov 22 15:33:38 2020
$end
$version
	Icarus Verilog
$end
$timescale
	1ps
$end
$scope module testbench $end
$var wire 8 ! program_byte [7:0] $end
$var wire 4 " Operand [3:0] $end
$var wire 4 # Intrucciones [3:0] $end
$var reg 1 $ clk $end
$var reg 12 % count [11:0] $end
$var reg 1 & eneable_counter $end
$var reg 1 ' eneable_fetch $end
$var reg 1 ( load $end
$var reg 1 ) reset $end
$scope module c1 $end
$var wire 1 $ clk $end
$var wire 1 & eneable_counter $end
$var wire 1 ' eneable_fetch $end
$var wire 1 ( load $end
$var wire 1 ) reset $end
$var wire 12 * valor [11:0] $end
$var wire 8 + prog_b [7:0] $end
$var wire 4 , oprnd [3:0] $end
$var wire 4 - instr [3:0] $end
$var wire 12 . count_w [11:0] $end
$scope module c0 $end
$var wire 12 / b [11:0] $end
$var wire 1 & clk $end
$var wire 1 ( eneable $end
$var wire 1 $ load $end
$var wire 1 ) reset $end
$var reg 12 0 c [11:0] $end
$upscope $end
$scope module f0 $end
$var wire 1 $ clk2 $end
$var wire 1 ' eneable2 $end
$var wire 1 ) reset2 $end
$var wire 8 1 D [7:0] $end
$var reg 4 2 Q0 [3:0] $end
$var reg 4 3 Q1 [3:0] $end
$upscope $end
$scope module r0 $end
$var wire 8 4 dato [7:0] $end
$var wire 12 5 direccion [11:0] $end
$upscope $end
$upscope $end
$upscope $end
$enddefinitions $end
#0
$dumpvars
bx 5
bx 4
b0 3
b0 2
bx 1
bx 0
b0 /
bx .
b0 -
b0 ,
bx +
b0 *
1)
1(
0'
0&
b0 %
0$
b0 #
b0 "
bx !
$end
#1
bx !
bx +
bx 1
bx 4
bx .
bx 0
bx 5
1$
0)
#2
0$
0(
#3
b1111 !
b1111 +
b1111 1
b1111 4
b0 .
b0 0
b0 5
1$
1&
#4
0$
b1 %
b1 *
b1 /
#5
b11110000 !
b11110000 +
b11110000 1
b11110000 4
b1 .
b1 0
b1 5
b1111 "
b1111 ,
b1111 3
1$
1'
#6
0$
#7
b1111 #
b1111 -
b1111 2
b0 "
b0 ,
b0 3
1$
#8
0$
#9
1$
#10
0$
#11
1$
#12
0$
#13
1$
#14
0$
#15
1$
0&
#16
0$
#17
1$
#18
0$
#19
1$
#20
0$
#21
b1111 !
b1111 +
b1111 1
b1111 4
b0 .
b0 0
b0 5
b0 #
b0 -
b0 2
1$
1)
#22
0$
1(
#23
1$
0(
#24
0$
0)
#25
b11110000 !
b11110000 +
b11110000 1
b11110000 4
b1 .
b1 0
b1 5
b1111 "
b1111 ,
b1111 3
1$
#26
0$
#27
b1111 #
b1111 -
b1111 2
b0 "
b0 ,
b0 3
1$
1&
