Laboratorio_05/Ejercicio5.v
//Laboratorio_5, Ejercicio 5
//Daniel Mundo
//19508
//Electronica Digital 1, seccion 11
// Mux 2:1
module Mux2(input wire I0, I1, s0, output wire y0);
  assign Y = s0 ? I1 : I0;                            //defino los parametros y la ecuacion del mux 2:1
endmodule

//Mux 4:1
module Mux4(input wire w0, w1, w2, w3, s0, s1, output wire y1);
  wire m0, m1;
  Mux2 u0(w0, w1, s0, m0);                            //realizo la operacion con tres mux 2:1 para tener
  Mux2 u1(w2, w3, s0, m1);                           // dos condiciones y cuatro entradas
  Mux2 u2(m0, m1, s1, y1);
endmodule

//Mux 8:1
module Mux8(input wire d0, d1, d2, d3, d4, d5, d6, d7, s0, s1, s2, output wire y2);
  wire n0, n1;
  Mux4 u3(d0, d1, d2, d3, s0, s1, n0);                  //realizo la operacion con dos mux 4:1 & un mux 2:1
  Mux4 u4(d4, d5, d6, d7, s0, s1, n1);                 //tres condiciones y ocho entradas
  Mux2 u5(n0, n1, s2, y);
endmodule

//Aplicacion tabla 01
module T1M8(input wire A, B, C, output wire Y0);
  wire l, h;
  assign l = 1'b0;
  assign h = 1'b1;
  Mux8 N1(l, h, h, l, h, l, l, h, A, B, C, Y0);
endmodule

module T1M4(input wire A, B, C, output wire Y1);
  wire w0;
  assign w0 = ~C;
  Mux4 N1(C, w0, w0, C, A, B, Y1);
endmodule

module T1M2(input wire A, B, C, output wire Y2);
  wire w2, w3;
  assign w2 = B * ~C + ~B * C;
  assign w3 = ~w2;
  Mux2 N2(w2, w3, A, Y2);
endmodule

//Aplicacion tabla 02
module T2M8(input wire A, B, C, output wire Y3);
  wire L, H;
  assign L = 1'b0;
  assign H = 1'b1;
  Mux8 N3 (H, L, L, L, L, H, H, L, A, B, C, Y3);
endmodule

module T2M4(input wire A, B, C, output wire Y4);
  wire w4;
  assign w5 = ~C;
  Mux4 N4( 1'b1, 1'b0, 1'b1, w5, A, B, Y4);
endmodule

module T2M2(input wire A, B, C, output wire Y5);
  wire w6, w7;
  assign w6 = B & ~C || ~B & C;
  assign w7 = ~(C | B);
  Mux2 N5(w7, w6, A, Y5);
endmodule

Laboratorio_05/Ejercicio5_tb.v
//Modulo para la condiciones de las entradas
//Entradas: A, B, C - Salida: Y
module testbench();                       //Declaracion de entradas y salidas
  reg A, B, C, D, E, F;                        //A0, B0, C0, A1, B1, C1, A2, B2, C2,
              //Entradas
  wire Y0, Y1, Y2, Y3, Y4, Y5;    //Salidas
//Modulos de 'Ejercicio5.v'
  //Mux2  M0);
  //Mux4  M1;
  //Mux8  M2;
  T1M2  T0(A, B, C, Y0);
  T1M4  T1(A, B, C, Y1);
  T1M8  T2(A, B, C, Y2);
  T2M2  T3(D, E, F, Y3);
  T2M4  T4(D, E, F, Y4);
  T2M8  T5(D, E, F, Y5);

  initial begin                             //IMPLEMENTACION DE TABLA 01

    $display("Tabla 01");
    $display("Mux 2:1            Mux 4:1            Mux 8:1" );
    $display("------             -------            --------");
    $monitor("%b %b %b | %b   %b %b %b | %b       %b %b %b | %b",
              A, B, C, Y0, A, B, C, Y1, A, B, C, Y2);
        A=0; B=0; C=0;
    #1  A=0; B=0; C=1;
    #1  A=0; B=1; C=1;
    #1  A=0; B=1; C=0;
    #1  A=1; B=1; C=0;
    #1  A=1; B=0; C=0;
    #1  A=1; B=0; C=1;
    #1  A=1; B=1; C=1;
  end

  initial begin                             //IMPLEMENTACION DE TABLA 02
    #8
    $display("Tabla 02");
    $display("Mux 2:1            Mux 4:1            Mux 8:1" );
    $display("-------------   --------------      -----------");
    $monitor("%b %b %b | %b   %b %b %b | %b       %b %b %b | %b",
              D, E, F, Y3, D, E, F, Y4, D, E, F, Y5);
          D=0; E=0; F=0;
      #1  D=0; E=0; F=1;
      #1  D=0; E=1; F=1;
      #1  D=0; E=1; F=0;
      #1  D=1; E=1; F=0;
      #1  D=1; E=0; F=0;
      #1  D=1; E=0; F=1;
      #1  D=1; E=1; F=1;
    end

    initial                                  //Finalizacion de las condiciones
      #20 $finish;

  initial begin
    $dumpfile("Ejercicio5_tb.vcd");
    $dumpvars(0, testbench);
  end
endmodule

Laboratorio_05/Ejercicio5_tb.vcd
$date
	Sun Aug 16 11:38:53 2020
$end
$version
	Icarus Verilog
$end
$timescale
	1ps
$end
$scope module testbench $end
$var wire 1 ! Y0 $end
$var wire 1 " Y1 $end
$var wire 1 # Y2 $end
$var wire 1 $ Y3 $end
$var wire 1 % Y4 $end
$var wire 1 & Y5 $end
$var reg 1 ' A $end
$var reg 1 ( B $end
$var reg 1 ) C $end
$var reg 1 * D $end
$var reg 1 + E $end
$var reg 1 , F $end
$scope module T0 $end
$var wire 1 ' A $end
$var wire 1 ( B $end
$var wire 1 ) C $end
$var wire 1 ! Y2 $end
$var wire 1 - w3 $end
$var wire 1 . w2 $end
$scope module N2 $end
$var wire 1 . I0 $end
$var wire 1 - I1 $end
$var wire 1 ' s0 $end
$var wire 1 ! y0 $end
$var wire 1 / Y $end
$upscope $end
$upscope $end
$scope module T1 $end
$var wire 1 ' A $end
$var wire 1 ( B $end
$var wire 1 ) C $end
$var wire 1 " Y1 $end
$var wire 1 0 w0 $end
$scope module N1 $end
$var wire 1 1 m0 $end
$var wire 1 2 m1 $end
$var wire 1 ' s0 $end
$var wire 1 ( s1 $end
$var wire 1 ) w0 $end
$var wire 1 0 w1 $end
$var wire 1 0 w2 $end
$var wire 1 ) w3 $end
$var wire 1 " y1 $end
$scope module u0 $end
$var wire 1 ) I0 $end
$var wire 1 0 I1 $end
$var wire 1 ' s0 $end
$var wire 1 1 y0 $end
$var wire 1 3 Y $end
$upscope $end
$scope module u1 $end
$var wire 1 0 I0 $end
$var wire 1 ) I1 $end
$var wire 1 ' s0 $end
$var wire 1 2 y0 $end
$var wire 1 4 Y $end
$upscope $end
$scope module u2 $end
$var wire 1 1 I0 $end
$var wire 1 2 I1 $end
$var wire 1 ( s0 $end
$var wire 1 " y0 $end
$var wire 1 5 Y $end
$upscope $end
$upscope $end
$upscope $end
$scope module T2 $end
$var wire 1 ' A $end
$var wire 1 ( B $end
$var wire 1 ) C $end
$var wire 1 # Y0 $end
$var wire 1 6 h $end
$var wire 1 7 l $end
$scope module N1 $end
$var wire 1 7 d0 $end
$var wire 1 6 d1 $end
$var wire 1 6 d2 $end
$var wire 1 7 d3 $end
$var wire 1 6 d4 $end
$var wire 1 7 d5 $end
$var wire 1 7 d6 $end
$var wire 1 6 d7 $end
$var wire 1 8 n0 $end
$var wire 1 9 n1 $end
$var wire 1 ' s0 $end
$var wire 1 ( s1 $end
$var wire 1 ) s2 $end
$var wire 1 : y $end
$var wire 1 # y2 $end
$scope module u3 $end
$var wire 1 ; m0 $end
$var wire 1 < m1 $end
$var wire 1 ' s0 $end
$var wire 1 ( s1 $end
$var wire 1 7 w0 $end
$var wire 1 6 w1 $end
$var wire 1 6 w2 $end
$var wire 1 7 w3 $end
$var wire 1 8 y1 $end
$scope module u0 $end
$var wire 1 7 I0 $end
$var wire 1 6 I1 $end
$var wire 1 ' s0 $end
$var wire 1 ; y0 $end
$var wire 1 = Y $end
$upscope $end
$scope module u1 $end
$var wire 1 6 I0 $end
$var wire 1 7 I1 $end
$var wire 1 ' s0 $end
$var wire 1 < y0 $end
$var wire 1 > Y $end
$upscope $end
$scope module u2 $end
$var wire 1 ; I0 $end
$var wire 1 < I1 $end
$var wire 1 ( s0 $end
$var wire 1 8 y0 $end
$var wire 1 ? Y $end
$upscope $end
$upscope $end
$scope module u4 $end
$var wire 1 @ m0 $end
$var wire 1 A m1 $end
$var wire 1 ' s0 $end
$var wire 1 ( s1 $end
$var wire 1 6 w0 $end
$var wire 1 7 w1 $end
$var wire 1 7 w2 $end
$var wire 1 6 w3 $end
$var wire 1 9 y1 $end
$scope module u0 $end
$var wire 1 6 I0 $end
$var wire 1 7 I1 $end
$var wire 1 ' s0 $end
$var wire 1 @ y0 $end
$var wire 1 B Y $end
$upscope $end
$scope module u1 $end
$var wire 1 7 I0 $end
$var wire 1 6 I1 $end
$var wire 1 ' s0 $end
$var wire 1 A y0 $end
$var wire 1 C Y $end
$upscope $end
$scope module u2 $end
$var wire 1 @ I0 $end
$var wire 1 A I1 $end
$var wire 1 ( s0 $end
$var wire 1 9 y0 $end
$var wire 1 D Y $end
$upscope $end
$upscope $end
$scope module u5 $end
$var wire 1 8 I0 $end
$var wire 1 9 I1 $end
$var wire 1 ) s0 $end
$var wire 1 : y0 $end
$var wire 1 E Y $end
$upscope $end
$upscope $end
$upscope $end
$scope module T3 $end
$var wire 1 * A $end
$var wire 1 + B $end
$var wire 1 , C $end
$var wire 1 $ Y5 $end
$var wire 1 F w6 $end
$var wire 1 G w7 $end
$scope module N5 $end
$var wire 1 G I0 $end
$var wire 1 F I1 $end
$var wire 1 * s0 $end
$var wire 1 $ y0 $end
$var wire 1 H Y $end
$upscope $end
$upscope $end
$scope module T4 $end
$var wire 1 * A $end
$var wire 1 + B $end
$var wire 1 , C $end
$var wire 1 % Y4 $end
$var wire 1 I w5 $end
$scope module N4 $end
$var wire 1 J m0 $end
$var wire 1 K m1 $end
$var wire 1 * s0 $end
$var wire 1 + s1 $end
$var wire 1 L w0 $end
$var wire 1 M w1 $end
$var wire 1 N w2 $end
$var wire 1 I w3 $end
$var wire 1 % y1 $end
$scope module u0 $end
$var wire 1 L I0 $end
$var wire 1 M I1 $end
$var wire 1 * s0 $end
$var wire 1 J y0 $end
$var wire 1 O Y $end
$upscope $end
$scope module u1 $end
$var wire 1 N I0 $end
$var wire 1 I I1 $end
$var wire 1 * s0 $end
$var wire 1 K y0 $end
$var wire 1 P Y $end
$upscope $end
$scope module u2 $end
$var wire 1 J I0 $end
$var wire 1 K I1 $end
$var wire 1 + s0 $end
$var wire 1 % y0 $end
$var wire 1 Q Y $end
$upscope $end
$upscope $end
$upscope $end
$scope module T5 $end
$var wire 1 * A $end
$var wire 1 + B $end
$var wire 1 , C $end
$var wire 1 R H $end
$var wire 1 S L $end
$var wire 1 & Y3 $end
$scope module N3 $end
$var wire 1 R d0 $end
$var wire 1 S d1 $end
$var wire 1 S d2 $end
$var wire 1 S d3 $end
$var wire 1 S d4 $end
$var wire 1 R d5 $end
$var wire 1 R d6 $end
$var wire 1 S d7 $end
$var wire 1 T n0 $end
$var wire 1 U n1 $end
$var wire 1 * s0 $end
$var wire 1 + s1 $end
$var wire 1 , s2 $end
$var wire 1 V y $end
$var wire 1 & y2 $end
$scope module u3 $end
$var wire 1 W m0 $end
$var wire 1 X m1 $end
$var wire 1 * s0 $end
$var wire 1 + s1 $end
$var wire 1 R w0 $end
$var wire 1 S w1 $end
$var wire 1 S w2 $end
$var wire 1 S w3 $end
$var wire 1 T y1 $end
$scope module u0 $end
$var wire 1 R I0 $end
$var wire 1 S I1 $end
$var wire 1 * s0 $end
$var wire 1 W y0 $end
$var wire 1 Y Y $end
$upscope $end
$scope module u1 $end
$var wire 1 S I0 $end
$var wire 1 S I1 $end
$var wire 1 * s0 $end
$var wire 1 X y0 $end
$var wire 1 Z Y $end
$upscope $end
$scope module u2 $end
$var wire 1 W I0 $end
$var wire 1 X I1 $end
$var wire 1 + s0 $end
$var wire 1 T y0 $end
$var wire 1 [ Y $end
$upscope $end
$upscope $end
$scope module u4 $end
$var wire 1 \ m0 $end
$var wire 1 ] m1 $end
$var wire 1 * s0 $end
$var wire 1 + s1 $end
$var wire 1 S w0 $end
$var wire 1 R w1 $end
$var wire 1 R w2 $end
$var wire 1 S w3 $end
$var wire 1 U y1 $end
$scope module u0 $end
$var wire 1 S I0 $end
$var wire 1 R I1 $end
$var wire 1 * s0 $end
$var wire 1 \ y0 $end
$var wire 1 ^ Y $end
$upscope $end
$scope module u1 $end
$var wire 1 R I0 $end
$var wire 1 S I1 $end
$var wire 1 * s0 $end
$var wire 1 ] y0 $end
$var wire 1 _ Y $end
$upscope $end
$scope module u2 $end
$var wire 1 \ I0 $end
$var wire 1 ] I1 $end
$var wire 1 + s0 $end
$var wire 1 U y0 $end
$var wire 1 ` Y $end
$upscope $end
$upscope $end
$scope module u5 $end
$var wire 1 T I0 $end
$var wire 1 U I1 $end
$var wire 1 , s0 $end
$var wire 1 V y0 $end
$var wire 1 a Y $end
$upscope $end
$upscope $end
$upscope $end
$upscope $end
$enddefinitions $end
#0
$dumpvars
za
z`
x_
x^
z]
z\
z[
0Z
xY
zX
zW
zV
zU
zT
0S
1R
zQ
xP
xO
1N
0M
1L
zK
zJ
xI
xH
xG
xF
zE
zD
0C
1B
zA
z@
z?
1>
0=
z<
z;
z:
z9
z8
07
16
z5
14
03
z2
z1
10
0/
0.
1-
x,
x+
x*
0)
0(
0'
z&
z%
z$
z#
z"
z!
$end
#1
04
1/
0-
00
13
1.
1)
#2
0/
1-
0.
1(
#3
1/
0-
14
1.
10
03
0)
#4
0/
13
04
1=
0>
0B
1C
1'
#5
1/
1-
0.
0(
#6
0/
03
0-
00
14
1.
1)
#7
1/
1-
0.
1(
#8
1H
0F
1G
1I
1O
1P
1Y
0^
1_
0,
0+
0*
#9
0H
1F
0G
0I
1,
#10
0F
1+
#11
1F
1I
0,
#12
1H
0O
0Y
1^
0_
1*
#13
0H
0F
1G
0+
#14
1H
1F
0G
0P
0I
1,
#15
0H
0F
1+
