Laboratorio_09/Ejercicio 1/Ejercicio1.v
//Ejercicio 1: Flip Flop Tipo D de dos salidas
//Daniel Mundo
module FlipFlopD(input eneable, reset, clk, input D, output reg Q);
  always @ (posedge clk, posedge reset)
  begin
    if (reset) Q <= 1'b0;
    else if (eneable) Q <= D;
    end
endmodule //El modulo describe que durante el flanco positivo de "clk" va reali-
        //zar la operacion de comprobar si "reset" esta encendido o no, en caso
        //afirmativo la salida "Q" es igual a 0 sino es igual al valor en ese
        //instante de la entrada "D".
module FlipFlopD2(input eneable2, reset2, clk2,
                  input [1:0]D2, output wire [1:0]Q2);
  FlipFlopD f1(eneable2, reset2, clk2, D2[0], Q2[0]);
  FlipFlopD f2(eneable2, reset2, clk2, D2[1], Q2[1]);
endmodule   //Este modulo llama dos veces al modulo de FlipFlopD, lo que dife-
            //rencia a los dos modulos llamados es la entrada "D" y salida "Q".
module FlipFlopD4(input eneable3, reset3, clk3, input [3:0]D3,
                  output wire [3:0]Q3);
  FlipFlopD2 f3(eneable3, reset3, clk3, D3[1:0], Q3[1:0]);
  FlipFlopD2 f4(eneable3, reset3, clk3, D3[3:2], Q3[3:2]);
endmodule //Este modulo al igual que el anterior llama 2 veces al modulo
          //FlipFlopD2, teniendo asi una salida "Q" de 4 bits.

Laboratorio_09/Ejercicio 1/Ejercicio1_tb.v
// Test bench: Ejercicio 1
//Daniel Mundo 19508
module testbench();
reg [3:0]D;
reg clk;
reg reset;
reg eneable;
wire [3:0]Q; //Se define el tipo de "variable" con las cuales va a trabajar
            //el modulo.
FlipFlopD4 f1(eneable, reset, clk, D[3:0], Q[3:0]);
FlipFlopD2 f2(eneable, reset, clk, D[1:0], Q[1:0]);
FlipFlopD f3(eneable, reset, clk, D[0], Q[0]); //Se llaman a los modulos.
initial begin
clk = 0; reset = 1; eneable = 0; D=4'b1;
#1 reset = 0;
#5 eneable = 1; D=4'b0010;
#3 D=3'b0;
#4 eneable = 0; D=4'b0011;
#6 reset = 1;
#3 eneable = 1; reset = 0; D=3'b0100;
#10 $finish;
end //Es el apartado de las pruebas asignadoles valores a las entradas.
always
#1 clk = !clk;//Se invierte el valor de clk, para simular una verdadera
              //señal de reloj.
initial begin
  $dumpfile("Ejercicio1_tb.vcd");
  $dumpvars(0, testbench);
end //Se crea el archivo para mostrar las pruebas.
endmodule

Laboratorio_09/Ejercicio 1/Ejercicio1_tb.vcd
$date
	Sat Oct 31 01:43:25 2020
$end
$version
	Icarus Verilog
$end
$timescale
	1ps
$end
$scope module testbench $end
$var wire 4 ! Q [3:0] $end
$var reg 4 " D [3:0] $end
$var reg 1 # clk $end
$var reg 1 $ eneable $end
$var reg 1 % reset $end
$scope module f1 $end
$var wire 4 & D3 [3:0] $end
$var wire 4 ' Q3 [3:0] $end
$var wire 1 # clk3 $end
$var wire 1 $ eneable3 $end
$var wire 1 % reset3 $end
$scope module f3 $end
$var wire 2 ( D2 [1:0] $end
$var wire 1 # clk2 $end
$var wire 1 $ eneable2 $end
$var wire 1 % reset2 $end
$var wire 2 ) Q2 [1:0] $end
$scope module f1 $end
$var wire 1 * D $end
$var wire 1 # clk $end
$var wire 1 $ eneable $end
$var wire 1 % reset $end
$var reg 1 + Q $end
$upscope $end
$scope module f2 $end
$var wire 1 , D $end
$var wire 1 # clk $end
$var wire 1 $ eneable $end
$var wire 1 % reset $end
$var reg 1 - Q $end
$upscope $end
$upscope $end
$scope module f4 $end
$var wire 2 . D2 [1:0] $end
$var wire 1 # clk2 $end
$var wire 1 $ eneable2 $end
$var wire 1 % reset2 $end
$var wire 2 / Q2 [1:0] $end
$scope module f1 $end
$var wire 1 0 D $end
$var wire 1 # clk $end
$var wire 1 $ eneable $end
$var wire 1 % reset $end
$var reg 1 1 Q $end
$upscope $end
$scope module f2 $end
$var wire 1 2 D $end
$var wire 1 # clk $end
$var wire 1 $ eneable $end
$var wire 1 % reset $end
$var reg 1 3 Q $end
$upscope $end
$upscope $end
$upscope $end
$scope module f2 $end
$var wire 2 4 D2 [1:0] $end
$var wire 1 # clk2 $end
$var wire 1 $ eneable2 $end
$var wire 1 % reset2 $end
$var wire 2 5 Q2 [1:0] $end
$scope module f1 $end
$var wire 1 6 D $end
$var wire 1 # clk $end
$var wire 1 $ eneable $end
$var wire 1 % reset $end
$var reg 1 7 Q $end
$upscope $end
$scope module f2 $end
$var wire 1 8 D $end
$var wire 1 # clk $end
$var wire 1 $ eneable $end
$var wire 1 % reset $end
$var reg 1 9 Q $end
$upscope $end
$upscope $end
$scope module f3 $end
$var wire 1 : D $end
$var wire 1 # clk $end
$var wire 1 $ eneable $end
$var wire 1 % reset $end
$var reg 1 ; Q $end
$upscope $end
$upscope $end
$enddefinitions $end
#0
$dumpvars
0;
1:
09
08
07
16
b0 5
b1 4
03
02
01
00
b0 /
b0 .
0-
0,
0+
1*
b0 )
b1 (
b0 '
b1 &
1%
0$
0#
b1 "
b0 !
$end
#1
1#
0%
#2
0#
#3
1#
#4
0#
#5
1#
#6
06
18
0*
1,
b10 4
0:
b10 (
0#
b10 "
b10 &
1$
#7
b10 )
1-
b10 !
b10 '
b10 5
19
1#
#8
0#
#9
08
0,
b0 4
b0 (
1#
b0 "
b0 &
#10
0#
#11
b0 )
0-
b0 !
b0 '
b0 5
09
1#
#12
0#
#13
16
18
1*
1,
b11 4
1:
b11 (
1#
b11 "
b11 &
0$
#14
0#
#15
1#
#16
0#
#17
1#
#18
0#
#19
1#
1%
#20
0#
#21
1#
#22
06
08
0*
0,
10
b0 4
0:
b0 (
b1 .
0#
b100 "
b100 &
0%
1$
#23
b100 !
b100 '
b1 /
11
1#
