Laboratorio_04/Ejercicio_5/modulo05.v
//Ejercicio 5
//Gate level Modelling (GM)
    //POS
module  POS_GM(input wire A, B, C, output wire Y);
  wire notA, notB, notC, w1, w2, w3, w4, w5;
  not (notA, A);
  not (notB, B);
  not (notC, C);
  or (w1, A, B, C);
  or (w2, A, B, notC);
  or (w3, A, notB, notC);
  or (w4, A, notB, C);
  or (w5, notA, notB, C);
  and (Y, w1, w2, w3, w4, w5);
endmodule

    //SOP
module  SOP_GM(input wire A, B, C, output wire Y);
  wire notB, notC, w1, w2, w3;
  not (notB, B);
  not (notC, C);
  and (w1, A, notB, notC);
  and (w2, A, notB, C);
  and (w3, A, B, C);
  or  (Y, w1, w2, w3);
endmodule

    //Ecuacion reducida (ER)
module  ER_GM(input wire A, B, C, output wire Y);
  wire notB, w1, w2;
  not (notB, B);
  and (w1, A, notB);
  and (w2, A, C);
  or  (Y, w1, w2);
endmodule

//Behavorial Modelling (BM)
      //POS
module  POS_BM(input wire A, B, C, output wire Y);
  assign Y = (A | B | C) & (A | B | ~C) & (A | ~B | ~C) & (A | ~B | C) & (~A | ~B | C);
endmodule

      //SOP
module  SOP_BM(input wire A, B, C, output wire Y);
  assign Y = (A & ~B & ~C) | (A & ~B & C) | (A & B & C);
endmodule

      //Ecuacion reducida (ER)
module  ER_BM(input wire A, B, C, output wire Y);
  assign Y = (A & ~B) | (A & C);
endmodule

Laboratorio_04/Ejercicio_5/modulo05_tb.v
//Modulo para la condiciones de las entradas
//Entradas: A, B, C, D - Salida: Y
module testbench();                       //Declaracion de entradas y salidas
  reg A1, B1, C1,
      A2, B2, C2,
      A3, B3, C3,
      A4, B4, C4,
      A5, B5, C5,
      A6, B6, C6;                  //Entradas
  wire Y1, Y2, Y3, Y4, Y5, Y6;    //Salidas
//Modulos de 'modulo05.v'
  POS_GM  P1(A1, B1, C1, Y1);
  SOP_GM  S1(A2, B2, C2, Y2);
  ER_GM   E1(A3, B3, C3, Y3);
  POS_BM  P2(A4, B4, C4, Y4);
  SOP_BM  S2(A5, B5, C5, Y5);
  ER_BM   E2(A6, B6, C6, Y6);

  initial begin                             //POS_GM
    $display("POS");
    $display("A B C | Y");
    $display("------|--");
    $monitor("%b %b %b | %b", A1, B1, C1, Y1);
        A1=0; B1=0; C1=0;
    #1  A1=0; B1=0; C1=1;
    #1  A1=0; B1=1; C1=1;
    #1  A1=0; B1=1; C1=0;
    #1  A1=1; B1=1; C1=0;
    #1  A1=1; B1=0; C1=0;
    #1  A1=1; B1=0; C1=1;
    #1  A1=1; B1=1; C1=1;
  end

  initial begin                             //SOP_GM
    #8
    $display("SOP");
    $display("A B C | Y");
    $display("------|--");
    $monitor("%b %b %b | %b", A2, B2, C2, Y2);
        A2=0; B2=0; C2=0;
    #1  A2=0; B2=0; C2=1;
    #1  A2=0; B2=1; C2=1;
    #1  A2=0; B2=1; C2=0;
    #1  A2=1; B2=1; C2=0;
    #1  A2=1; B2=0; C2=0;
    #1  A2=1; B2=0; C2=1;
    #1  A2=1; B2=1; C2=1;
  end

  initial begin                             //ER_GM
    #16
    $display("Ecuacion reducida");
    $display("A B C | Y");
    $display("------|--");
    $monitor("%b %b %b | %b", A3, B3, C3, Y3);
        A3=0; B3=0; C3=0;
    #1  A3=0; B3=0; C3=1;
    #1  A3=0; B3=1; C3=1;
    #1  A3=0; B3=1; C3=0;
    #1  A3=1; B3=1; C3=0;
    #1  A3=1; B3=0; C3=0;
    #1  A3=1; B3=0; C3=1;
    #1  A3=1; B3=1; C3=1;
  end

  initial begin                             //POS_BM
    #32
    $display("POS");
    $display("A B C | Y");
    $display("------|--");
    $monitor("%b %b %b | %b", A4, B4, C4, Y4);
        A4=0; B4=0; C4=0;
    #1  A4=0; B4=0; C4=1;
    #1  A4=0; B4=1; C4=1;
    #1  A4=0; B4=1; C4=0;
    #1  A4=1; B4=1; C4=0;
    #1  A4=1; B4=0; C4=0;
    #1  A4=1; B4=0; C4=1;
    #1  A4=1; B4=1; C4=1;
  end

  initial begin                             //SOP_BM
    #40
    $display("SOP");
    $display("A B C | Y");
    $display("------|--");
    $monitor("%b %b %b | %b", A5, B5, C5, Y5);
        A5=0; B5=0; C5=0;
    #1  A5=0; B5=0; C5=1;
    #1  A5=0; B5=1; C5=1;
    #1  A5=0; B5=1; C5=0;
    #1  A5=1; B5=1; C5=0;
    #1  A5=1; B5=0; C5=0;
    #1  A5=1; B5=0; C5=1;
    #1  A5=1; B5=1; C5=1;
  end

  initial begin                             //ER_BM
      #48
      $display("Ecuacion reducida");
      $display("A B C | Y");
      $display("------|--");
      $monitor("%b %b %b | %b", A6, B6, C6, Y6);
          A6=0; B6=0; C6=0;
      #1  A6=0; B6=0; C6=1;
      #1  A6=0; B6=1; C6=1;
      #1  A6=0; B6=1; C6=0;
      #1  A6=1; B6=1; C6=0;
      #1  A6=1; B6=0; C6=0;
      #1  A6=1; B6=0; C6=1;
      #1  A6=1; B6=1; C6=1;
    end

    initial                                  //Finalizacion de las condiciones
      #56 $finish;

  initial begin
    $dumpfile("modulo05_tb.vcd");
    $dumpvars(0, testbench);
  end
endmodule

Laboratorio_04/Ejercicio_5/modulo05_tb.vcd
$date
	Sun Aug 09 20:14:14 2020
$end
$version
	Icarus Verilog
$end
$timescale
	1ps
$end
$scope module testbench $end
$var wire 1 ! Y6 $end
$var wire 1 " Y5 $end
$var wire 1 # Y4 $end
$var wire 1 $ Y3 $end
$var wire 1 % Y2 $end
$var wire 1 & Y1 $end
$var reg 1 ' A1 $end
$var reg 1 ( A2 $end
$var reg 1 ) A3 $end
$var reg 1 * A4 $end
$var reg 1 + A5 $end
$var reg 1 , A6 $end
$var reg 1 - B1 $end
$var reg 1 . B2 $end
$var reg 1 / B3 $end
$var reg 1 0 B4 $end
$var reg 1 1 B5 $end
$var reg 1 2 B6 $end
$var reg 1 3 C1 $end
$var reg 1 4 C2 $end
$var reg 1 5 C3 $end
$var reg 1 6 C4 $end
$var reg 1 7 C5 $end
$var reg 1 8 C6 $end
$scope module E1 $end
$var wire 1 ) A $end
$var wire 1 / B $end
$var wire 1 5 C $end
$var wire 1 $ Y $end
$var wire 1 9 notB $end
$var wire 1 : w1 $end
$var wire 1 ; w2 $end
$upscope $end
$scope module E2 $end
$var wire 1 , A $end
$var wire 1 2 B $end
$var wire 1 8 C $end
$var wire 1 ! Y $end
$upscope $end
$scope module P1 $end
$var wire 1 ' A $end
$var wire 1 - B $end
$var wire 1 3 C $end
$var wire 1 & Y $end
$var wire 1 < notA $end
$var wire 1 = notB $end
$var wire 1 > notC $end
$var wire 1 ? w1 $end
$var wire 1 @ w2 $end
$var wire 1 A w3 $end
$var wire 1 B w4 $end
$var wire 1 C w5 $end
$upscope $end
$scope module P2 $end
$var wire 1 * A $end
$var wire 1 0 B $end
$var wire 1 6 C $end
$var wire 1 # Y $end
$upscope $end
$scope module S1 $end
$var wire 1 ( A $end
$var wire 1 . B $end
$var wire 1 4 C $end
$var wire 1 % Y $end
$var wire 1 D notB $end
$var wire 1 E notC $end
$var wire 1 F w1 $end
$var wire 1 G w2 $end
$var wire 1 H w3 $end
$upscope $end
$scope module S2 $end
$var wire 1 + A $end
$var wire 1 1 B $end
$var wire 1 7 C $end
$var wire 1 " Y $end
$upscope $end
$upscope $end
$enddefinitions $end
#0
$dumpvars
xH
xG
xF
xE
xD
1C
1B
1A
1@
0?
1>
1=
1<
x;
x:
x9
x8
x7
x6
x5
x4
03
x2
x1
x0
x/
x.
0-
x,
x+
x*
x)
x(
0'
0&
x%
x$
x#
x"
x!
$end
#1
0&
0@
0>
1?
13
#2
0&
0A
0=
1@
1-
#3
1A
1>
0B
03
#4
0&
0C
0<
1B
1'
#5
1&
1C
1=
0-
#6
0>
13
#7
0=
1-
#8
0%
1E
1D
0F
0G
0H
04
0.
0(
#9
0E
14
#10
0D
1.
#11
1E
04
#12
1(
#13
1%
1F
1D
0.
#14
0F
0E
1G
14
#15
0G
0D
1H
1.
#16
0$
19
0:
0;
05
0/
0)
#17
15
#18
09
1/
#19
05
#20
1)
#21
1$
1:
19
0/
#22
1;
15
#23
0:
09
1/
#32
0#
06
00
0*
#33
16
#34
10
#35
06
#36
1*
#37
1#
00
#38
16
#39
10
#40
0"
07
01
0+
#41
17
#42
11
#43
07
#44
1+
#45
1"
01
#46
17
#47
11
#48
0!
08
02
0,
#49
18
#50
12
#51
08
#52
1,
#53
1!
02
#54
18
#55
12
