Laboratorio_09/Ejercicio 3/Ejercicio3.v
//Ejercicio 3: Flip Flop Tipo JK
//Daniel Mundo 19508
module FlipFlopD(input e, r, c, input d, output reg q);
  always @ (posedge c, posedge r)
  begin
    if (r) q <= 1'b0;
    else if (e) q <= d;
    end
endmodule//Del ejercicio 1, el funcionamiento se explica en el archivo:
        // "Ejercicio1.v" carpeta Ejercicio 1.
module Combination(input wire j, k, q,output wire D);
  //Cables auxiliares
  wire notk, notq, y0, y1;
//Niegan las entradas
  not n1(notk, k);
  not n2(notq, q);
//Operacion D = ~K*Q + J*~Q
  and a1(y0, notk, q);
  and a2(y1, j, notq);
  or  o1(D, y1, y0);
endmodule //En este modulo se describe de manera estructural la nube combinacio-
        //nal que va conectada antes del FlipFlop tipo D.
module FlipFlopJK(input eneable, reset, clk, input J, K, output wire Q);
  wire y;
  FlipFlopD   f1(eneable, reset, clk, y, Q);
  Combination m1(J, K, Q, y);
endmodule //En este modulo se une la salida de la nube combinacional a la entra-
        //das "D" del Flip FLop tipo D, teniendo tambien, dicha nube combinacio-
      //nal como parte de sus entradas la salida "Q" del FlipFlop.

Laboratorio_09/Ejercicio 3/Ejercicio3_tb.v
//Test Bench: Ejercicio 3
module testbench();
reg J, K;
reg clk;
reg reset;
reg eneable;
wire Q;  //Se define el tipo de "variable" con las cuales va a trabajar
        //el modulo.
FlipFlopJK f2(eneable, reset, clk, J, K, Q); //Se llama al modulo.
initial begin
clk = 0; reset = 1; eneable = 1; J=0; K=0;
#1 reset = 0; J=1;
#5 K=1;
#3 J=0;
#3 J=1;
#5 $finish;
end //Es el apartado de las pruebas asignadoles valores a las entradas.
always
#1 clk = !clk;
//Se invierte el valor de clk, para simular una verdadera señal de reloj.
initial begin
  $dumpfile("Ejercicio3_tb.vcd");
  $dumpvars(0, testbench);
end //Se crea el archivo para mostrar las pruebas.
endmodule

Laboratorio_09/Ejercicio 3/Ejercicio3_tb.vcd
$date
	Sat Oct 31 02:23:34 2020
$end
$version
	Icarus Verilog
$end
$timescale
	1ps
$end
$scope module testbench $end
$var wire 1 ! Q $end
$var reg 1 " J $end
$var reg 1 # K $end
$var reg 1 $ clk $end
$var reg 1 % eneable $end
$var reg 1 & reset $end
$scope module f2 $end
$var wire 1 " J $end
$var wire 1 # K $end
$var wire 1 $ clk $end
$var wire 1 % eneable $end
$var wire 1 & reset $end
$var wire 1 ' y $end
$var wire 1 ! Q $end
$scope module f1 $end
$var wire 1 $ c $end
$var wire 1 % e $end
$var wire 1 & r $end
$var wire 1 ' d $end
$var reg 1 ! q $end
$upscope $end
$scope module m1 $end
$var wire 1 ' D $end
$var wire 1 " j $end
$var wire 1 # k $end
$var wire 1 ( notk $end
$var wire 1 ) notq $end
$var wire 1 ! q $end
$var wire 1 * y0 $end
$var wire 1 + y1 $end
$upscope $end
$upscope $end
$upscope $end
$enddefinitions $end
#0
$dumpvars
0+
0*
1)
1(
0'
1&
1%
0$
0#
0"
0!
$end
#1
1'
1+
1$
1"
0&
#2
0$
#3
0+
0)
1*
1!
1$
#4
0$
#5
1$
#6
0'
0*
0(
0$
1#
#7
1'
1+
1)
0!
1$
#8
0$
#9
0)
1!
0'
0+
1$
0"
#10
0$
#11
1)
0!
1$
#12
1'
1+
0$
1"
#13
0'
0+
0)
1!
1$
#14
0$
#15
1'
1+
1)
0!
1$
#16
0$
#17
0'
0+
0)
1!
1$
