Laboratorio_10/Ejercicio_2/ALU.v
//Ejercicio 2: Circuito 2; ALU, Acumulador & Buffers Triestado
//Daniel Mundo 19508
module ACU(input wire [3:0]D, input wire eneable, reset, clk, output reg [3:0]Q);
  always @ (posedge clk, posedge reset) begin
    if (reset) Q <= 0;
    else if (eneable) begin
        Q <= D;
    end
  end
endmodule //Es parecido a un FlipFlop tipo D de cuatro bits de  entrada y salida,
          //si el bit eneable esta en uno deja pasar la entrada D y si reset es-
          //ta en uno limpia la salida.
module ALU_aritmetica(input wire [3:0] A,B, input wire [2:0] Select,
                      output wire Zero, Carry, output wire [3:0] Y ); //B corresponde a la
                      //salida del ACU.
  reg [4:0] Oprnd;
  assign Zero = ~(Y[3]|Y[2]|Y[1]|Y[0]); //Solo si todos los bits son cero, Zero esta en 1.
  assign Carry = Oprnd[4]; //Se enciende solo si el quinto bit de Oprnd es 1.
  assign Y = Oprnd[4:0];
  always @ (A, B, Select) begin // siempre que cambie control, A o B.
    case (Select)
      3'b000: Oprnd <= A; //Deja pasar A
      3'b001: Oprnd <= A-B; //Resta A con B, tambien sirve para saber si A > B
      3'b010: Oprnd <= B; //Deja pasar B
      3'b011: Oprnd <= A+B; //Adiciona A con B
      3'b100: Oprnd <= ~(A|B); //NOR de A y B
      default: Oprnd <= 0;
    endcase
  end
endmodule
module Circuito2(input [3:0]DataIn, input [2:0] Select, input clk, reset, enTri, enACU,
                 output wire [3:0] DataOut, output wire Z, C);
  wire [3:0] ALUOut, ACUOut;
  ALU_aritmetica A1(ACUOut, DataIn, Select, Z, C, ALUOut);
  Buffer4bits busDriver(enTri, ALUOut, DataOut);
  ACU A0(ALUOut, enACU, reset, clk, ACUOut);

endmodule //

Laboratorio_10/Ejercicio_2/TriEstado.v
//Ejercicio 3: Tri Estado de 4 bits
//Daniel Mundo 19508
module Buffer4bits(input T, input [3:0]I, output wire [3:0]Y);
  assign Y = (T) ? I: 4'bz ;
endmodule //El modulo realiza la operecion que mientras "T" sea 0 la salida "Y"
        //va a estar en alta impedancia, en caso contrario sera el valor que
        // tenga en ese instante la entrada "I".

Laboratorio_10/Ejercicio_2/ALU_tb.v
//Circuito 2; ALU, Acumulador & Buffers Triestado
module testbench();
reg[3:0] B;
reg[2:0] S;
reg eneableOut, eneableACU, reset, clk;
wire[3:0] Out;
wire C,Z;
Circuito2 c2(B, S, reset, clk, eneableOut, eneableACU, Out, Z, C);
initial begin
reset=0; eneableACU=0; eneableOut=0; S=0; B= 0; clk = 0;
#1 reset=1;
#1 reset=0;
#1 B= 10;
#2 eneableOut = 1;
#2 S = 0; //deja pasar el dato de 10
#1 eneableACU = 1;
#1 eneableACU = 0;  //valor actual del acumulador es 10
#1 B= 10;
#1 S = 1; //resta acumulador - B, Zero se enciende
#1 eneableACU = 1;
#1 eneableACU = 0; //se carga el valor en el acumulador valor 0
#1 B = 15;
#1 S = 2; //deja pasar B
#1 eneableACU = 1;
#1 eneableACU = 0;// acumulador en 15
#1 eneableOut = 0; //bus driver alu en alta impedancia
#1 eneableOut = 1; //valor de salida de la ALU
#2 B = 1;
#1 S = 3; //se suma acumulador y B, se enciende Carry
#1 eneableACU = 1; //se carga 1 al acumulador
#1 eneableACU = 0;
#2 S = 4;  //NOR entre acu y el dato de entrada
#1 reset = 1;
#1 S = 0;
#1 $finish;
end
always
#1 clk = !clk;//Se invierte el valor de clk, parBsimular unBverdader señal de relo
initial begin
       $dumpfile("ALU_tb.vcd");
       $dumpvars(0,testbench);
end
endmodule

Laboratorio_10/Ejercicio_2/ALU_tb.vcd
$date
	Sat Nov 07 22:09:15 2020
$end
$version
	Icarus Verilog
$end
$timescale
	1ps
$end
$scope module testbench $end
$var wire 1 ! Z $end
$var wire 4 " Out [3:0] $end
$var wire 1 # C $end
$var reg 4 $ B [3:0] $end
$var reg 3 % S [2:0] $end
$var reg 1 & clk $end
$var reg 1 ' eneableACU $end
$var reg 1 ( eneableOut $end
$var reg 1 ) reset $end
$scope module c2 $end
$var wire 4 * DataIn [3:0] $end
$var wire 3 + Select [2:0] $end
$var wire 1 ) clk $end
$var wire 1 ' enACU $end
$var wire 1 ( enTri $end
$var wire 1 & reset $end
$var wire 1 ! Z $end
$var wire 4 , DataOut [3:0] $end
$var wire 1 # C $end
$var wire 4 - ALUOut [3:0] $end
$var wire 4 . ACUOut [3:0] $end
$scope module A0 $end
$var wire 1 ) clk $end
$var wire 1 ' eneable $end
$var wire 1 & reset $end
$var wire 4 / D [3:0] $end
$var reg 4 0 Q [3:0] $end
$upscope $end
$scope module A1 $end
$var wire 4 1 A [3:0] $end
$var wire 4 2 B [3:0] $end
$var wire 3 3 Select [2:0] $end
$var wire 1 ! Zero $end
$var wire 4 4 Y [3:0] $end
$var wire 1 # Carry $end
$var reg 5 5 Oprnd [4:0] $end
$upscope $end
$scope module busDriver $end
$var wire 4 6 I [3:0] $end
$var wire 1 ( T $end
$var wire 4 7 Y [3:0] $end
$upscope $end
$upscope $end
$upscope $end
$enddefinitions $end
#0
$dumpvars
bz 7
bx 6
b0xxxx 5
bx 4
b0 3
b0 2
bx 1
bx 0
bx /
bx .
bx -
bz ,
b0 +
b0 *
0)
0(
0'
0&
b0 %
b0 $
0#
bz "
x!
$end
#1
1!
b0 -
b0 /
b0 4
b0 6
b0 5
b0 .
b0 0
b0 1
1&
1)
#2
0&
0)
#3
1&
b1010 $
b1010 *
b1010 2
#4
0&
#5
b0 "
b0 ,
b0 7
1&
1(
#6
0&
#7
1&
#8
0&
1'
#9
1&
0'
#10
0&
#11
0!
b110 "
b110 ,
b110 7
1#
b110 -
b110 /
b110 4
b110 6
b10110 5
1&
b1 %
b1 +
b1 3
#12
0&
1'
#13
1&
0'
#14
b1 "
b1 ,
b1 7
b1 -
b1 /
b1 4
b1 6
b10001 5
0&
b1111 $
b1111 *
b1111 2
#15
b1111 "
b1111 ,
b1111 7
0#
b1111 -
b1111 /
b1111 4
b1111 6
b1111 5
1&
b10 %
b10 +
b10 3
#16
0&
1'
#17
1&
0'
#18
bz "
bz ,
bz 7
0&
0(
#19
b1111 "
b1111 ,
b1111 7
1&
1(
#20
0&
#21
b1 "
b1 ,
b1 7
b1 -
b1 /
b1 4
b1 6
b1 5
1&
b1 $
b1 *
b1 2
#22
0&
b11 %
b11 +
b11 3
#23
1&
1'
#24
0&
0'
#25
1&
#26
b1110 "
b1110 ,
b1110 7
1#
b1110 -
b1110 /
b1110 4
b1110 6
b11110 5
0&
b100 %
b100 +
b100 3
#27
1&
1)
#28
1!
b0 "
b0 ,
b0 7
0#
b0 -
b0 /
b0 4
b0 6
b0 5
0&
b0 %
b0 +
b0 3
