Laboratorio_03/T3_POS/T3POS.v
//Nombre del modulo
module T3POS();

// Entradas
reg a, b, c, d;
// Salidas
wire M1, M2, M3, M4, M5, M6, M7, M8, M9;
wire notA, notB, notC, notD;
wire Y;

// Negacion de entradas
not N1(notA, a);
not N2(notB, b);
not N3(notC, c);
not N4(notD, d);

// Maxterminos
or O1(M1, a, notB, c, d);
or O2(M2, a, notB, c, notD);
or O3(M3, a, notB, notC, d);
or O4(M4, a, notB, notC, notD);
or O5(M5, notA, b, c, notD);
or O6(M6, notA, b, notC, notD);
or O7(M7, notA, notB, c, d);
or O8(M8, notA, notB, c, notD);
or O9(M9, notA, notB, notC, notD);
and A10(Y, M1, M2, M3, M4, M5, M6, M7, M8, M9);

//Condiciones
initial begin
  $monitor ("a=%b, b=%b, c=%b, d=%b, Y=%b", a, b, c, d, Y);
  a =0; b =0; c =0; d=0;
  #1 a =1;                             //1000
  #1 a =0; b =1;                       //0100
  #1 b =0; c =1;                       //0010
  #1 c =0; d =1;                       //0001
  #1 c =1;                             //0011
  #1 a =1; c =0;                       //1001
  #1 a =0; b =1;                       //0101
  #1 a =1; d =0;                       //1100
  #1 a =0; c =1;                       //0110
  #1 a =1; b =0;                       //1010
  #1 a =0; b =1; d =1;                 //0111
  #1 a =1; b =0;                       //1011
  #1 b =1; c =0;                       //1101
  #1 c =1; d =0;                       //1110
  #1 d =1; $finish;                    //1111
end

initial
  begin
    $dumpfile("T3POS_tb.vcd");
    $dumpvars(0, T3POS);
  end
endmodule

Laboratorio_03/T3_POS/T3POS_tb.vcd
$date
	Sun Aug 02 17:05:48 2020
$end
$version
	Icarus Verilog
$end
$timescale
	1ps
$end
$scope module T3POS $end
$var wire 1 ! M1 $end
$var wire 1 " M2 $end
$var wire 1 # M3 $end
$var wire 1 $ M4 $end
$var wire 1 % M5 $end
$var wire 1 & M6 $end
$var wire 1 ' M7 $end
$var wire 1 ( M8 $end
$var wire 1 ) M9 $end
$var wire 1 * Y $end
$var wire 1 + notA $end
$var wire 1 , notB $end
$var wire 1 - notC $end
$var wire 1 . notD $end
$var reg 1 / a $end
$var reg 1 0 b $end
$var reg 1 1 c $end
$var reg 1 2 d $end
$upscope $end
$enddefinitions $end
#0
$dumpvars
02
01
00
0/
1.
1-
1,
1+
1*
1)
1(
1'
1&
1%
1$
1#
1"
1!
$end
#1
0+
1/
#2
0*
0!
0,
1+
10
0/
#3
1*
1!
0-
1,
11
00
#4
0.
1-
12
01
#5
0-
11
#6
0*
0%
1-
0+
01
1/
#7
0"
1%
0,
1+
10
0/
#8
0'
1.
1"
0+
02
1/
#9
0#
1'
0-
1+
11
0/
#10
1*
1,
1#
0+
00
1/
#11
0*
0$
0.
0,
1+
12
10
0/
#12
0&
1,
1$
0+
00
1/
#13
0(
1-
1&
0,
01
10
#14
1*
1.
1(
0-
02
11
#15
0*
0)
0.
12
