Laboratorio_08/Ejercicio_3/Ejercicio3.v
//Ejercicio 3: ALU
//Daniel Mundo 19508
//Se implementa una ALU de modo behavorial
module ALU(input [2:0] Select,
           input [3:0] A, B,
           output [3:0] Out,
           output CarryOut);
  wire [4:0]carry;
  reg [3:0]result;
  assign Out = result;
  assign carry = {1'b0, A}+{1'b0, B};
  assign CarryOut = carry[4];
  always @ ( * )
  begin
    case (Select)
    3'b000: //A AND B
      result = A & B;
    3'b001: //A OR B
      result = A | B;
    3'b010: //A + B
      result = A + B;
    3'b011: //no se utiliza, debe de poner en uno toda la salida
      result = 4'b1111;
    3'b100: //A AND B'
      result = A & ~B;
    3'b101:  //A OR B'
      result = A | ~B;
    3'b110: //A - B
      result = A - B;
    3'b111: //SLT
      result = (A<B)? 4'd1:4'd0;
    default:result = A & B;
    endcase
  end
endmodule //

Laboratorio_08/Ejercicio_3/Ejercicio3_tb.v
//ejercicio 3
module testbench();

reg [3:0] A, B;
reg [2:0] S;

wire [3:0] O;
wire C;
integer i;
ALU a1(S,A,B,O,C);

initial
begin
S = 3'b0;
A = 4'd10;
B = 4'd6;

for (i=0; i<=7;i=i+1)
begin
S = S + 3'd1;
#10;
end

A = 4'd10;
B= 4'd16;

end

initial begin
       $dumpfile("Ejercicio3_tb.vcd");
       $dumpvars(0,testbench);
   end

endmodule

Laboratorio_08/Ejercicio_3/Ejercicio3_tb.vcd
$date
	Sat Oct 24 17:59:19 2020
$end
$version
	Icarus Verilog
$end
$timescale
	1ps
$end
$scope module testbench $end
$var wire 4 ! O [3:0] $end
$var wire 1 " C $end
$var reg 4 # A [3:0] $end
$var reg 4 $ B [3:0] $end
$var reg 3 % S [2:0] $end
$var integer 32 & i [31:0] $end
$scope module a1 $end
$var wire 4 ' A [3:0] $end
$var wire 4 ( B [3:0] $end
$var wire 4 ) Out [3:0] $end
$var wire 3 * Select [2:0] $end
$var wire 5 + carry [4:0] $end
$var wire 1 " CarryOut $end
$var reg 4 , result [3:0] $end
$upscope $end
$upscope $end
$enddefinitions $end
#0
$dumpvars
b1110 ,
b10000 +
b1 *
b1110 )
b110 (
b1010 '
b0 &
b1 %
b110 $
b1010 #
1"
b1110 !
$end
#10
b0 !
b0 )
b0 ,
b10 %
b10 *
b1 &
#20
b1111 !
b1111 )
b1111 ,
b11 %
b11 *
b10 &
#30
b1000 !
b1000 )
b1000 ,
b100 %
b100 *
b11 &
#40
b1011 !
b1011 )
b1011 ,
b101 %
b101 *
b100 &
#50
b100 !
b100 )
b100 ,
b110 %
b110 *
b101 &
#60
b0 !
b0 )
b0 ,
b111 %
b111 *
b110 &
#70
b10 !
b10 )
b10 ,
b0 %
b0 *
b111 &
#80
b0 !
b0 )
b0 ,
0"
b1010 +
b0 $
b0 (
b1000 &
